nbdep/__init__.py
nbdep/_modidx.py
nbdep/pipfile.py
nbdep-0.0.1.dist-info/LICENSE
nbdep-0.0.1.dist-info/METADATA
nbdep-0.0.1.dist-info/WHEEL
nbdep-0.0.1.dist-info/entry_points.txt
nbdep-0.0.1.dist-info/top_level.txt
nbdep-0.0.1.dist-info/RECORD
